mtm/__init__.py
mtm/console.py
mtm/definition.py
mtm/machine.py
mtm/tape.py
mtm/examples/__init__.py
mtm/examples/abc_equal.py
mtm/examples/palindrome_2tape.py
mtm/examples/ww_delimiter.py
multitape_tm-1.0.4.dist-info/licenses/LICENSE
multitape_tm-1.0.4.dist-info/METADATA
multitape_tm-1.0.4.dist-info/WHEEL
multitape_tm-1.0.4.dist-info/top_level.txt
multitape_tm-1.0.4.dist-info/RECORD
