Metadata-Version: 2.4
Name: multitape-tm
Version: 1.0.4
Summary: Multi-tape Turing Machine simulator in Python
Author-email: Luisangel Alexander Parra Faria <hello@luisangelparra.com>
License: Apache-2.0
Project-URL: Homepage, https://github.com/LuisangelParra/mtm
Project-URL: Source, https://github.com/LuisangelParra/mtm
Keywords: turing machine,automata,complexity theory,multi-tape
Classifier: Programming Language :: Python :: 3
Classifier: Programming Language :: Python :: 3.14
Classifier: License :: OSI Approved :: Apache Software License
Classifier: Intended Audience :: Education
Classifier: Topic :: Scientific/Engineering :: Mathematics
Requires-Python: >=3.14
License-File: LICENSE
Dynamic: license-file
